nx_migrate/__init__.py
nx_migrate/nx_migrate.py
nx_migrate-0.3.1.dist-info/LICENSE
nx_migrate-0.3.1.dist-info/METADATA
nx_migrate-0.3.1.dist-info/WHEEL
nx_migrate-0.3.1.dist-info/entry_points.txt
nx_migrate-0.3.1.dist-info/RECORD
